{"responses":{"200":{"description":"Proctoring data retrieved successfully","content":{"application/json":{"schema":{"type":"object","required":["success","message","data"],"properties":{"success":{"type":"boolean","example":true},"message":{"type":"string","example":"Recording details retrieved successfully"},"data":{"type":"object","required":["clientId","interviewId","details"],"properties":{"clientId":{"type":"string"},"interviewId":{"type":"string"},"details":{"type":"object"}}}},"title":"ProctoringDataSuccessResponse"}}}},"401":{"description":"Unauthorized","content":{"application/json":{"schema":{"type":"object","properties":{"error":{"type":"string","example":"Unauthorized"}},"title":"UnauthorizedError"}}}},"404":{"description":"Interview or proctoring data not found","content":{"application/json":{"schema":{"type":"object","required":["success","message","error"],"properties":{"success":{"type":"boolean","example":false},"message":{"type":"string","example":"Error retrieving recording details"},"error":{"type":"object","required":["code","details"],"properties":{"code":{"type":"string"},"details":{"type":"string"}}}},"title":"ProctoringDataErrorResponse"}}}},"500":{"description":"Internal server error","content":{"application/json":{"schema":{"type":"object","required":["success","message","error"],"properties":{"success":{"type":"boolean","example":false},"message":{"type":"string","example":"Error retrieving recording details"},"error":{"type":"object","required":["code","details"],"properties":{"code":{"type":"string"},"details":{"type":"string"}}}},"title":"ProctoringDataErrorResponse"}}}}}}